Seq_Y86/ALU/Adder_and_Subtractor/FullAdder.v
module FullAdder (
    input A, B, Cin,
    output Cout, Sum
);
    wire w1, w2, w3;

    xor x1(Sum, A, B, Cin);
    
    and x2(w1, A, B);
    and x3(w2, Cin, B);
    and x4(w3, A, Cin);
    
    or x5(Cout, w1, w2, w3);
endmodule

Seq_Y86/ALU/Adder_and_Subtractor/FullAdder_tb.v
`include "FullAdder.v"

module FullAdder_tb;
    reg A,B,Cin;
    wire Cout,Sum;

    FullAdder x1(.A(A), .B(B), .Cin(Cin), .Cout(Cout), .Sum(Sum));

    initial begin
        $dumpfile("FullAdder.vcd");
        $dumpvars(0, FullAdder_tb);

        $monitor("At Time = %2t: A = %d, B = %d, Cin = %d, Cout = %d, Sum = %d", $time, A, B, Cin, Cout, Sum);
        
        #2 A = 0;B = 0;Cin = 0; /*Ans: Cout = 0,Sum = 0*/
        #2 A = 0;B = 0;Cin = 1; /*Ans: Cout = 0,Sum = 1*/
        #2 A = 0;B = 1;Cin = 0; /*Ans: Cout = 0,Sum = 1*/
        #2 A = 0;B = 1;Cin = 1; /*Ans: Cout = 1,Sum = 0*/
        #2 A = 1;B = 0;Cin = 0; /*Ans: Cout = 0,Sum = 1*/
        #2 A = 1;B = 0;Cin = 1; /*Ans: Cout = 1,Sum = 0*/
        #2 A = 1;B = 1;Cin = 0; /*Ans: Cout = 1,Sum = 0*/
        #2 A = 1;B = 1;Cin = 1; /*Ans: Cout = 1,Sum = 1*/
        #2 $finish;
    end
endmodule

ALU/Adder_and_Subtractor/FullAdder.vcd
$date
	Sun Feb 18 21:29:37 2024
$end
$version
	Icarus Verilog
$end
$timescale
	1s
$end
$scope module FullAdder_tb $end
$var wire 1 ! Sum $end
$var wire 1 " Cout $end
$var reg 1 # A $end
$var reg 1 $ B $end
$var reg 1 % Cin $end
$scope module x1 $end
$var wire 1 # A $end
$var wire 1 $ B $end
$var wire 1 % Cin $end
$var wire 1 " Cout $end
$var wire 1 ! Sum $end
$var wire 1 & w1 $end
$var wire 1 ' w2 $end
$var wire 1 ( w3 $end
$upscope $end
$upscope $end
$enddefinitions $end
#0
$dumpvars
x(
x'
x&
x%
x$
x#
x"
x!
$end
#2
0"
0'
0!
0&
0(
0%
0$
0#
#4
1!
1%
#6
0%
1$
#8
1"
0!
1'
1%
#10
0"
0'
1!
0%
0$
1#
#12
1"
0!
1(
1%
#14
0(
1&
0%
1$
#16
1!
1'
1(
1%
