Pipe_Y86/ALU/Logical_Xor/Xor.v
module Xor (In1,In2,Out,Overflow);
    parameter N = 64;
    input [N-1:0] In1,In2;
    output [N-1:0]Out;
    output Overflow;

    genvar i;
    generate
        for (i = 0; i < 64; i = i + 1)
            xor x1(Out[i], In1[i], In2[i]);
    endgenerate
    assign Overflow = 1'b0;
endmodule

ALU/Logical_Xor/Xor_tb.v
`include "Xor.v"

module Xor_tb;
    reg [63:0] In1,In2;
    wire [63:0] Out;

    Xor dut(.In1(In1), .In2(In2), .Out(Out),.Overflow(Overflow));

    initial
    begin
        $dumpfile("Xor.vcd");
        $dumpvars(0, Xor_tb);

        $monitor("At Time = %2t:\n \tIn1 = %64b (%d),\n \tIn2 = %64b (%d),\n \tOut = %64b (%d),\n \tOverflow = %b", $time, In1, In1, In2, In2, Out, Out, Overflow);
        
        #2 In1 = 64'b0011000101010110100110010000011100001110010001001011101000101011; In2 = 64'b0010100101001000010101111001100000100010110100110111100001010001;
        #2 In1 = 64'b1001101010110110000010111111100100011110100100011001000011111111; In2 = 64'b0100001100001110000011010011110111010011110110100101101001001100;
        #2 In1 = 64'b1011011111111011011000100100101111111010101101001011100001010110; In2 = 64'b0010101111111100000011011011111101001010101011111101010010110101;
        #2 In1 = 64'b0101111110010100100111010101011010001111010011101011110111000001; In2 = 64'b0001111100101110100111111011001101111100100100111111000110100101;
        #2 In1 = 64'b1011010111100010111011101100000011100010110010110011001010000001; In2 = 64'b1010010011000110100000000011110011100011011111011111010010111110;
        #2 In1 = 64'b0111001101001111110010100011100001101011111100010000011111100111; In2 = 64'b0111011110101101001111110001010110010010001010110111000110001000;
        #2 In1 = 64'b1101101100000101000000000010011101011010000011010000001101000000; In2 = 64'b1010101110001011011000011010010011011011000111101000100010011111;
        #2 In1 = 64'b1111110110001001111111001110011000000001111111000000100000101010; In2 = 64'b0000011110101011101000011111011111011101001001010011001011001000;
        #2 In1 = 64'b1001011111100101011101101101011100000100101000101001101011010101; In2 = 64'b1011001101101110001011011010000101010001101010110011011100001101;
        #2 In1 = 64'b1011001111000010101101100110110101110101100001011111000101001110; In2 = 64'b1001011111110010001010011001110100010101101100001101101011000011;
        #2 $finish;
    end
endmodule

ALU/Logical_Xor/Xor.vcd
$date
	Thu Feb 15 18:04:59 2024
$end
$version
	Icarus Verilog
$end
$timescale
	1s
$end
$scope module Xor_tb $end
$var wire 1 ! Overflow $end
$var wire 64 " Out [63:0] $end
$var reg 64 # In1 [63:0] $end
$var reg 64 $ In2 [63:0] $end
$scope module dut $end
$var wire 64 % In1 [63:0] $end
$var wire 64 & In2 [63:0] $end
$var wire 1 ! Overflow $end
$var wire 64 ' Out [63:0] $end
$scope begin genblk1[0] $end
$upscope $end
$scope begin genblk1[1] $end
$upscope $end
$scope begin genblk1[2] $end
$upscope $end
$scope begin genblk1[3] $end
$upscope $end
$scope begin genblk1[4] $end
$upscope $end
$scope begin genblk1[5] $end
$upscope $end
$scope begin genblk1[6] $end
$upscope $end
$scope begin genblk1[7] $end
$upscope $end
$scope begin genblk1[8] $end
$upscope $end
$scope begin genblk1[9] $end
$upscope $end
$scope begin genblk1[10] $end
$upscope $end
$scope begin genblk1[11] $end
$upscope $end
$scope begin genblk1[12] $end
$upscope $end
$scope begin genblk1[13] $end
$upscope $end
$scope begin genblk1[14] $end
$upscope $end
$scope begin genblk1[15] $end
$upscope $end
$scope begin genblk1[16] $end
$upscope $end
$scope begin genblk1[17] $end
$upscope $end
$scope begin genblk1[18] $end
$upscope $end
$scope begin genblk1[19] $end
$upscope $end
$scope begin genblk1[20] $end
$upscope $end
$scope begin genblk1[21] $end
$upscope $end
$scope begin genblk1[22] $end
$upscope $end
$scope begin genblk1[23] $end
$upscope $end
$scope begin genblk1[24] $end
$upscope $end
$scope begin genblk1[25] $end
$upscope $end
$scope begin genblk1[26] $end
$upscope $end
$scope begin genblk1[27] $end
$upscope $end
$scope begin genblk1[28] $end
$upscope $end
$scope begin genblk1[29] $end
$upscope $end
$scope begin genblk1[30] $end
$upscope $end
$scope begin genblk1[31] $end
$upscope $end
$scope begin genblk1[32] $end
$upscope $end
$scope begin genblk1[33] $end
$upscope $end
$scope begin genblk1[34] $end
$upscope $end
$scope begin genblk1[35] $end
$upscope $end
$scope begin genblk1[36] $end
$upscope $end
$scope begin genblk1[37] $end
$upscope $end
$scope begin genblk1[38] $end
$upscope $end
$scope begin genblk1[39] $end
$upscope $end
$scope begin genblk1[40] $end
$upscope $end
$scope begin genblk1[41] $end
$upscope $end
$scope begin genblk1[42] $end
$upscope $end
$scope begin genblk1[43] $end
$upscope $end
$scope begin genblk1[44] $end
$upscope $end
$scope begin genblk1[45] $end
$upscope $end
$scope begin genblk1[46] $end
$upscope $end
$scope begin genblk1[47] $end
$upscope $end
$scope begin genblk1[48] $end
$upscope $end
$scope begin genblk1[49] $end
$upscope $end
$scope begin genblk1[50] $end
$upscope $end
$scope begin genblk1[51] $end
$upscope $end
$scope begin genblk1[52] $end
$upscope $end
$scope begin genblk1[53] $end
$upscope $end
$scope begin genblk1[54] $end
$upscope $end
$scope begin genblk1[55] $end
$upscope $end
$scope begin genblk1[56] $end
$upscope $end
$scope begin genblk1[57] $end
$upscope $end
$scope begin genblk1[58] $end
$upscope $end
$scope begin genblk1[59] $end
$upscope $end
$scope begin genblk1[60] $end
$upscope $end
$scope begin genblk1[61] $end
$upscope $end
$scope begin genblk1[62] $end
$upscope $end
$scope begin genblk1[63] $end
$upscope $end
$upscope $end
$upscope $end
$enddefinitions $end
#0
$dumpvars
bx '
bx &
bx %
bx $
bx #
bx "
0!
$end
#2
b1100000011110110011101001111100101100100101111100001001111010 "
b1100000011110110011101001111100101100100101111100001001111010 '
b10100101001000010101111001100000100010110100110111100001010001 $
b10100101001000010101111001100000100010110100110111100001010001 &
b11000101010110100110010000011100001110010001001011101000101011 #
b11000101010110100110010000011100001110010001001011101000101011 %
#4
b1101100110111000000001101100010011001101010010111100101010110011 "
b1101100110111000000001101100010011001101010010111100101010110011 '
b100001100001110000011010011110111010011110110100101101001001100 $
b100001100001110000011010011110111010011110110100101101001001100 &
b1001101010110110000010111111100100011110100100011001000011111111 #
b1001101010110110000010111111100100011110100100011001000011111111 %
#6
b1001110000000111011011111111010010110000000110110110110011100011 "
b1001110000000111011011111111010010110000000110110110110011100011 '
b10101111111100000011011011111101001010101011111101010010110101 $
b10101111111100000011011011111101001010101011111101010010110101 &
b1011011111111011011000100100101111111010101101001011100001010110 #
b1011011111111011011000100100101111111010101101001011100001010110 %
#8
b100000010111010000000101110010111110011110111010100110001100100 "
b100000010111010000000101110010111110011110111010100110001100100 '
b1111100101110100111111011001101111100100100111111000110100101 $
b1111100101110100111111011001101111100100100111111000110100101 &
b101111110010100100111010101011010001111010011101011110111000001 #
b101111110010100100111010101011010001111010011101011110111000001 %
#10
b1000100100100011011101111110000000001101101101100011000111111 "
b1000100100100011011101111110000000001101101101100011000111111 '
b1010010011000110100000000011110011100011011111011111010010111110 $
b1010010011000110100000000011110011100011011111011111010010111110 &
b1011010111100010111011101100000011100010110010110011001010000001 #
b1011010111100010111011101100000011100010110010110011001010000001 %
#12
b10011100010111101010010110111111001110110100111011001101111 "
b10011100010111101010010110111111001110110100111011001101111 '
b111011110101101001111110001010110010010001010110111000110001000 $
b111011110101101001111110001010110010010001010110111000110001000 &
b111001101001111110010100011100001101011111100010000011111100111 #
b111001101001111110010100011100001101011111100010000011111100111 %
#14
b111000010001110011000011000001110000001000100111000101111011111 "
b111000010001110011000011000001110000001000100111000101111011111 '
b1010101110001011011000011010010011011011000111101000100010011111 $
b1010101110001011011000011010010011011011000111101000100010011111 &
b1101101100000101000000000010011101011010000011010000001101000000 #
b1101101100000101000000000010011101011010000011010000001101000000 %
#16
b1111101000100010010111010001000111011100110110010011101011100010 "
b1111101000100010010111010001000111011100110110010011101011100010 '
b11110101011101000011111011111011101001001010011001011001000 $
b11110101011101000011111011111011101001001010011001011001000 &
b1111110110001001111111001110011000000001111111000000100000101010 #
b1111110110001001111111001110011000000001111111000000100000101010 %
#18
b10010010001011010110110111011001010101000010011010110111011000 "
b10010010001011010110110111011001010101000010011010110111011000 '
b1011001101101110001011011010000101010001101010110011011100001101 $
b1011001101101110001011011010000101010001101010110011011100001101 &
b1001011111100101011101101101011100000100101000101001101011010101 #
b1001011111100101011101101101011100000100101000101001101011010101 %
#20
b10010000110000100111111111000001100000001101010010101110001101 "
b10010000110000100111111111000001100000001101010010101110001101 '
b1001011111110010001010011001110100010101101100001101101011000011 $
b1001011111110010001010011001110100010101101100001101101011000011 &
b1011001111000010101101100110110101110101100001011111000101001110 #
b1011001111000010101101100110110101110101100001011111000101001110 %
