Pipe_Y86/ALU/Logical_And/And.v
module And (In1,In2,Out,Overflow);
    parameter N = 64;
    input [N-1:0] In1,In2;
    output [N-1:0]Out;
    output Overflow;
    
    genvar i;
    generate
        for (i = 0; i < N; i = i + 1)
            and x1(Out[i], In1[i], In2[i]);
    endgenerate
    assign Overflow = 1'b0;
endmodule

Pipe_Y86/ALU/Logical_And/And_tb.v
`include "And.v"

module And_tb;
    reg [63:0] In1,In2;
    wire [63:0] Out;

    And dut(.In1(In1), .In2(In2), .Out(Out), .Overflow(Overflow));

    initial
    begin
        $dumpfile("And.vcd");
        $dumpvars(0, And_tb);

        $monitor("At Time = %2t:\n \tIn1 = %64b(%d),\n \tIn2 = %64b(%d),\n \tOut = %64b(%d),\n \tOverflow = %b", $time, In1, In1, In2, In2, Out, Out, Overflow);
        
        #2 In1 = 64'b0110001111000011001001100000101110100001010111011110000100010010; In2 = 64'b0100100010001101111011011001011000101001000011001010110001101000;
        #2 In1 = 64'b1100100111010011011010000011100111101011111010000011000101101101; In2 = 64'b1001100000000100001101100100001110110111110011011110000111000101;
        #2 In1 = 64'b1110110011010011010011001001010010000010010010100100111001011010; In2 = 64'b1010010001110111000011101000001001001100000101111100111111001100;
        #2 In1 = 64'b1111100010100110110110010010111010100001001010101101001110001000; In2 = 64'b1011010000001101101011111110100000010101100010000001001110001100;
        #2 In1 = 64'b1000000011010010100001000011001100001010011111000101000111010111; In2 = 64'b0100100110010101000100111110111111010111110101101110101100001011;
        #2 In1 = 64'b0110010101000101001001001101100101100100110011111100000101100111; In2 = 64'b1001101110110010010100011000111101110010001101110111110111101110;
        #2 In1 = 64'b0010000000101010100010000011000001100011111111011110010000000101; In2 = 64'b1110011000000001010011011110011011011110011001101111010010110010;
        #2 In1 = 64'b0010101101000011001001000011100100001111010100001000000101110100; In2 = 64'b1011001111001110000101110111101010100101110000100001100111100001;
        #2 In1 = 64'b1011000111100100001100000001000100000001011111010011000100101010; In2 = 64'b0010110000101100001010111001001011101110101011101010010111100001;
        #2 In1 = 64'b0111110000010001100001100011111111011011000101000111110101011001; In2 = 64'b1001001010100000100010011110111100010001110100110000101010111101;

        #2 $finish;
    end
endmodule

ALU/Logical_And/And.vcd
$date
	Thu Feb 15 18:04:18 2024
$end
$version
	Icarus Verilog
$end
$timescale
	1s
$end
$scope module And_tb $end
$var wire 1 ! Overflow $end
$var wire 64 " Out [63:0] $end
$var reg 64 # In1 [63:0] $end
$var reg 64 $ In2 [63:0] $end
$scope module dut $end
$var wire 64 % In1 [63:0] $end
$var wire 64 & In2 [63:0] $end
$var wire 1 ! Overflow $end
$var wire 64 ' Out [63:0] $end
$scope begin genblk1[0] $end
$upscope $end
$scope begin genblk1[1] $end
$upscope $end
$scope begin genblk1[2] $end
$upscope $end
$scope begin genblk1[3] $end
$upscope $end
$scope begin genblk1[4] $end
$upscope $end
$scope begin genblk1[5] $end
$upscope $end
$scope begin genblk1[6] $end
$upscope $end
$scope begin genblk1[7] $end
$upscope $end
$scope begin genblk1[8] $end
$upscope $end
$scope begin genblk1[9] $end
$upscope $end
$scope begin genblk1[10] $end
$upscope $end
$scope begin genblk1[11] $end
$upscope $end
$scope begin genblk1[12] $end
$upscope $end
$scope begin genblk1[13] $end
$upscope $end
$scope begin genblk1[14] $end
$upscope $end
$scope begin genblk1[15] $end
$upscope $end
$scope begin genblk1[16] $end
$upscope $end
$scope begin genblk1[17] $end
$upscope $end
$scope begin genblk1[18] $end
$upscope $end
$scope begin genblk1[19] $end
$upscope $end
$scope begin genblk1[20] $end
$upscope $end
$scope begin genblk1[21] $end
$upscope $end
$scope begin genblk1[22] $end
$upscope $end
$scope begin genblk1[23] $end
$upscope $end
$scope begin genblk1[24] $end
$upscope $end
$scope begin genblk1[25] $end
$upscope $end
$scope begin genblk1[26] $end
$upscope $end
$scope begin genblk1[27] $end
$upscope $end
$scope begin genblk1[28] $end
$upscope $end
$scope begin genblk1[29] $end
$upscope $end
$scope begin genblk1[30] $end
$upscope $end
$scope begin genblk1[31] $end
$upscope $end
$scope begin genblk1[32] $end
$upscope $end
$scope begin genblk1[33] $end
$upscope $end
$scope begin genblk1[34] $end
$upscope $end
$scope begin genblk1[35] $end
$upscope $end
$scope begin genblk1[36] $end
$upscope $end
$scope begin genblk1[37] $end
$upscope $end
$scope begin genblk1[38] $end
$upscope $end
$scope begin genblk1[39] $end
$upscope $end
$scope begin genblk1[40] $end
$upscope $end
$scope begin genblk1[41] $end
$upscope $end
$scope begin genblk1[42] $end
$upscope $end
$scope begin genblk1[43] $end
$upscope $end
$scope begin genblk1[44] $end
$upscope $end
$scope begin genblk1[45] $end
$upscope $end
$scope begin genblk1[46] $end
$upscope $end
$scope begin genblk1[47] $end
$upscope $end
$scope begin genblk1[48] $end
$upscope $end
$scope begin genblk1[49] $end
$upscope $end
$scope begin genblk1[50] $end
$upscope $end
$scope begin genblk1[51] $end
$upscope $end
$scope begin genblk1[52] $end
$upscope $end
$scope begin genblk1[53] $end
$upscope $end
$scope begin genblk1[54] $end
$upscope $end
$scope begin genblk1[55] $end
$upscope $end
$scope begin genblk1[56] $end
$upscope $end
$scope begin genblk1[57] $end
$upscope $end
$scope begin genblk1[58] $end
$upscope $end
$scope begin genblk1[59] $end
$upscope $end
$scope begin genblk1[60] $end
$upscope $end
$scope begin genblk1[61] $end
$upscope $end
$scope begin genblk1[62] $end
$upscope $end
$scope begin genblk1[63] $end
$upscope $end
$upscope $end
$upscope $end
$enddefinitions $end
#0
$dumpvars
bx '
bx &
bx %
bx $
bx #
bx "
0!
$end
#2
b100000010000001001001000000001000100001000011001010000000000000 "
b100000010000001001001000000001000100001000011001010000000000000 '
b100100010001101111011011001011000101001000011001010110001101000 $
b100100010001101111011011001011000101001000011001010110001101000 &
b110001111000011001001100000101110100001010111011110000100010010 #
b110001111000011001001100000101110100001010111011110000100010010 %
#4
b1000100000000000001000000000000110100011110010000010000101000101 "
b1000100000000000001000000000000110100011110010000010000101000101 '
b1001100000000100001101100100001110110111110011011110000111000101 $
b1001100000000100001101100100001110110111110011011110000111000101 &
b1100100111010011011010000011100111101011111010000011000101101101 #
b1100100111010011011010000011100111101011111010000011000101101101 %
#6
b1010010001010011000011001000000000000000000000100100111001001000 "
b1010010001010011000011001000000000000000000000100100111001001000 '
b1010010001110111000011101000001001001100000101111100111111001100 $
b1010010001110111000011101000001001001100000101111100111111001100 &
b1110110011010011010011001001010010000010010010100100111001011010 #
b1110110011010011010011001001010010000010010010100100111001011010 %
#8
b1011000000000100100010010010100000000001000010000001001110001000 "
b1011000000000100100010010010100000000001000010000001001110001000 '
b1011010000001101101011111110100000010101100010000001001110001100 $
b1011010000001101101011111110100000010101100010000001001110001100 &
b1111100010100110110110010010111010100001001010101101001110001000 #
b1111100010100110110110010010111010100001001010101101001110001000 %
#10
b10010000000000000010001100000010010101000100000100000011 "
b10010000000000000010001100000010010101000100000100000011 '
b100100110010101000100111110111111010111110101101110101100001011 $
b100100110010101000100111110111111010111110101101110101100001011 &
b1000000011010010100001000011001100001010011111000101000111010111 #
b1000000011010010100001000011001100001010011111000101000111010111 %
#12
b100000000000000001000100101100000000001110100000101100110 "
b100000000000000001000100101100000000001110100000101100110 '
b1001101110110010010100011000111101110010001101110111110111101110 $
b1001101110110010010100011000111101110010001101110111110111101110 &
b110010101000101001001001101100101100100110011111100000101100111 #
b110010101000101001001001101100101100100110011111100000101100111 %
#14
b10000000000000000010000010000001000010011001001110010000000000 "
b10000000000000000010000010000001000010011001001110010000000000 '
b1110011000000001010011011110011011011110011001101111010010110010 $
b1110011000000001010011011110011011011110011001101111010010110010 &
b10000000101010100010000011000001100011111111011110010000000101 #
b10000000101010100010000011000001100011111111011110010000000101 %
#16
b10001101000010000001000011100000000101010000000000000101100000 "
b10001101000010000001000011100000000101010000000000000101100000 '
b1011001111001110000101110111101010100101110000100001100111100001 $
b1011001111001110000101110111101010100101110000100001100111100001 &
b10101101000011001001000011100100001111010100001000000101110100 #
b10101101000011001001000011100100001111010100001000000101110100 %
#18
b10000000100100001000000001000000000000001011000010000100100000 "
b10000000100100001000000001000000000000001011000010000100100000 '
b10110000101100001010111001001011101110101011101010010111100001 $
b10110000101100001010111001001011101110101011101010010111100001 &
b1011000111100100001100000001000100000001011111010011000100101010 #
b1011000111100100001100000001000100000001011111010011000100101010 %
#20
b1000000000000100000000010111100010001000100000000100000011001 "
b1000000000000100000000010111100010001000100000000100000011001 '
b1001001010100000100010011110111100010001110100110000101010111101 $
b1001001010100000100010011110111100010001110100110000101010111101 &
b111110000010001100001100011111111011011000101000111110101011001 #
b111110000010001100001100011111111011011000101000111110101011001 %
